<work groupUrn="urn:cts:pompei:cil004-00400" xml:lang="None" urn="urn:cts:pompei:cil004-00400.00400" xmlns:cpt="http://purl.org/capitains/ns/1.0#" xmlns:dc="http://purl.org/dc/elements/1.1/" xmlns:rdfs="http://www.w3.org/2000/01/rdf-schema#" xmlns:rdf="http://www.w3.org/1999/02/22-rdf-syntax-ns#" xmlns:dts="http://w3id.org/dts-ontology/" xmlns="http://chs.harvard.edu/xmlns/cts" xmlns:saws="http://purl.org/saws/ontology#" xmlns:skos="http://www.w3.org/2004/02/skos/core#" xmlns:dct="http://purl.org/dc/terms/">
<title xml:lang="eng">00400</title>
<cpt:structured-metadata>
<rdfs:label xml:lang="eng">00400</rdfs:label>
<dc:identifier >EDCS-28000331</dc:identifier>
<saws:isLocatedAt >long:14.4891718;lat:40.7498815</saws:isLocatedAt>
<saws:identifier >www.trismegistos.org/text/523052</saws:identifier>
<saws:isLocatedAt >Pompei</saws:isLocatedAt>
<saws:isLocatedAt >http://www.trismegistos.org/place/2788</saws:isLocatedAt>
<skos:prefLabel xml:lang="eng">00400</skos:prefLabel>
</cpt:structured-metadata>
<edition xml:lang="lat" urn="urn:cts:pompei:cil004-00400.00400.manfred-lat1" workUrn="urn:cts:pompei:cil004-00400.00400">
<label xml:lang="eng">00400</label>
<description xml:lang="None">Automatically converted from Manfred Klaus database</description>
<cpt:structured-metadata>
<dct:contributor >Manfred Klaus</dct:contributor>
<dc:language >lat</dc:language>
<skos:prefLabel xml:lang="eng">00400</skos:prefLabel>
<dct:provenance >http://manfredclauss.de/gb/index.html</dct:provenance>
<dc:format >text/xml</dc:format>
<dct:source >http://www.worldcat.org/oclc/459220842</dct:source>
<dct:contributor >Thibault Clérice</dct:contributor>
<rdfs:label xml:lang="eng">00400</rdfs:label>
</cpt:structured-metadata>
</edition>
</work>