<work groupUrn="urn:cts:pompei:cil004-00000" xmlns:skos="http://www.w3.org/2004/02/skos/core#" urn="urn:cts:pompei:cil004-00000.00076" xmlns:saws="http://purl.org/saws/ontology#" xmlns:cpt="http://purl.org/capitains/ns/1.0#" xmlns:dc="http://purl.org/dc/elements/1.1/" xmlns="http://chs.harvard.edu/xmlns/cts" xmlns:rdf="http://www.w3.org/1999/02/22-rdf-syntax-ns#" xml:lang="None" xmlns:dts="http://w3id.org/dts-ontology/" xmlns:dct="http://purl.org/dc/terms/" xmlns:rdfs="http://www.w3.org/2000/01/rdf-schema#">
<title xml:lang="eng">00076</title>
<cpt:structured-metadata>
<rdfs:label xml:lang="eng">00076</rdfs:label>
<dc:identifier > CIL 01, 01640 (p 1015)</dc:identifier>
<skos:prefLabel xml:lang="eng">00076</skos:prefLabel>
<dc:identifier >EDCS-25800672</dc:identifier>
<saws:isLocatedAt >http://www.trismegistos.org/place/2788</saws:isLocatedAt>
<saws:isLocatedAt >Pompei</saws:isLocatedAt>
<saws:isLocatedAt >long:14.4891718;lat:40.7498815</saws:isLocatedAt>
<saws:identifier >www.trismegistos.org/text/T522730</saws:identifier>
</cpt:structured-metadata>
<edition urn="urn:cts:pompei:cil004-00000.00076.manfred-lat1" xml:lang="lat" workUrn="urn:cts:pompei:cil004-00000.00076">
<label xml:lang="eng">00076</label>
<description xml:lang="None">Automatically converted from Manfred Klaus database</description>
<cpt:structured-metadata>
<dct:contributor >Thibault Clérices</dct:contributor>
<dc:format >text/xml</dc:format>
<dct:contributor >Manfred Klaus</dct:contributor>
<skos:prefLabel xml:lang="eng">00076</skos:prefLabel>
<dct:source >http://www.worldcat.org/oclc/459220842</dct:source>
<dct:provenance >http://manfredclauss.de/gb/index.html</dct:provenance>
<dc:language >lat</dc:language>
<rdfs:label xml:lang="eng">00076</rdfs:label>
</cpt:structured-metadata>
</edition>
</work>